{
  "project_info": {
    "project_number": "475921655871",
    "firebase_url": "https://synapse-93496.firebaseio.com",
    "project_id": "synapse-93496",
    "storage_bucket": "synapse-93496.appspot.com"
  },
  "client": [
    {
      "client_info": {
        "mobilesdk_app_id": "1:475921655871:android:2b1aae1fa36b1ae758b08a",
        "android_client_info": {
          "package_name": "com.rthqks.synapse"
        }
      },
      "oauth_client": [
        {
          "client_id": "475921655871-hmq7g12csfmjs20la7mbe65dgmk0eovm.apps.googleusercontent.com",
          "client_type": 3
        }
      ],
      "api_key": [
        {
          "current_key": "AIzaSyBvP5qu2VBp-k-DYliLvfKFVY8RaxtW7mM"
        }
      ],
      "services": {
        "appinvite_service": {
          "other_platform_oauth_client": [
            {
              "client_id": "475921655871-hmq7g12csfmjs20la7mbe65dgmk0eovm.apps.googleusercontent.com",
              "client_type": 3
            }
          ]
        }
      }
    },
    {
      "client_info": {
        "mobilesdk_app_id": "1:475921655871:android:54ff8cd93d7cf6c358b08a",
        "android_client_info": {
          "package_name": "com.rthqks.synapse.debug"
        }
      },
      "oauth_client": [
        {
          "client_id": "475921655871-hmq7g12csfmjs20la7mbe65dgmk0eovm.apps.googleusercontent.com",
          "client_type": 3
        }
      ],
      "api_key": [
        {
          "current_key": "AIzaSyBvP5qu2VBp-k-DYliLvfKFVY8RaxtW7mM"
        }
      ],
      "services": {
        "appinvite_service": {
          "other_platform_oauth_client": [
            {
              "client_id": "475921655871-hmq7g12csfmjs20la7mbe65dgmk0eovm.apps.googleusercontent.com",
              "client_type": 3
            }
          ]
        }
      }
    },
    {
      "client_info": {
        "mobilesdk_app_id": "1:475921655871:android:0578bc9238d81b3258b08a",
        "android_client_info": {
          "package_name": "com.rthqks.synapse.next"
        }
      },
      "oauth_client": [
        {
          "client_id": "475921655871-hmq7g12csfmjs20la7mbe65dgmk0eovm.apps.googleusercontent.com",
          "client_type": 3
        }
      ],
      "api_key": [
        {
          "current_key": "AIzaSyBvP5qu2VBp-k-DYliLvfKFVY8RaxtW7mM"
        }
      ],
      "services": {
        "appinvite_service": {
          "other_platform_oauth_client": [
            {
              "client_id": "475921655871-hmq7g12csfmjs20la7mbe65dgmk0eovm.apps.googleusercontent.com",
              "client_type": 3
            }
          ]
        }
      }
    },
    {
      "client_info": {
        "mobilesdk_app_id": "1:475921655871:android:b0378a88c3e432d258b08a",
        "android_client_info": {
          "package_name": "com.rthqks.synapse.next.debug"
        }
      },
      "oauth_client": [
        {
          "client_id": "475921655871-hmq7g12csfmjs20la7mbe65dgmk0eovm.apps.googleusercontent.com",
          "client_type": 3
        }
      ],
      "api_key": [
        {
          "current_key": "AIzaSyBvP5qu2VBp-k-DYliLvfKFVY8RaxtW7mM"
        }
      ],
      "services": {
        "appinvite_service": {
          "other_platform_oauth_client": [
            {
              "client_id": "475921655871-hmq7g12csfmjs20la7mbe65dgmk0eovm.apps.googleusercontent.com",
              "client_type": 3
            }
          ]
        }
      }
    }
  ],
  "configuration_version": "1"
}